Metadata-Version: 2.1
Name: geodemoch
Version: 0.0.1
Summary: A test package for iteractive map display
Home-page: https://github.com/chebil med/geodemoch
Author: chebil
Author-email: medah12019@gmail.com
License: MIT license
Keywords: geodemoch
Platform: UNKNOWN
Classifier: Development Status :: 2 - Pre-Alpha
Classifier: Intended Audience :: Developers
Classifier: License :: OSI Approved :: MIT License
Classifier: Natural Language :: English
Classifier: Programming Language :: Python :: 3
Classifier: Programming Language :: Python :: 3.5
Classifier: Programming Language :: Python :: 3.6
Classifier: Programming Language :: Python :: 3.7
Classifier: Programming Language :: Python :: 3.8
Requires-Python: >=3.5
